karma/__init__.py
karma/benchmark.py
karma/cache/__init__.py
karma/cache/cache_manager.py
karma/cache/duckdb_cache_io.py
karma/cache/dynamodb_cache_io.py
karma/cli/__init__.py
karma/cli/main.py
karma/cli/orchestrator.py
karma/cli/utils.py
karma/cli/commands/__init__.py
karma/cli/commands/eval.py
karma/cli/commands/info.py
karma/cli/commands/interactive.py
karma/cli/commands/list.py
karma/cli/formatters/__init__.py
karma/cli/formatters/table.py
karma/data_models/__init__.py
karma/data_models/dataloader_iterable.py
karma/data_models/model_meta.py
karma/eval_datasets/__init__.py
karma/eval_datasets/base_dataset.py
karma/eval_datasets/clinical_note_generation_dataset.py
karma/eval_datasets/eka_med_asr_dataset.py
karma/eval_datasets/eka_retrieval_dataset.py
karma/eval_datasets/in22conv_dataset.py
karma/eval_datasets/indicvoices.py
karma/eval_datasets/indicvoices_r_dataset.py
karma/eval_datasets/medical_records_parsing_dataset.py
karma/eval_datasets/medmcqa_dataset.py
karma/eval_datasets/medmcqaindic_dataset.py
karma/eval_datasets/medqa_dataset.py
karma/eval_datasets/medxpertqa_dataset.py
karma/eval_datasets/mmlu_medical_datasets.py
karma/eval_datasets/nfimcqa_dataset.py
karma/eval_datasets/noise-evaluation-dataset.py
karma/eval_datasets/pubmedmcqa_dataset.py
karma/eval_datasets/slake_dataset.py
karma/eval_datasets/vistaar_small.py
karma/eval_datasets/vqa_rad_dataset.py
karma/eval_datasets/rubrics/__init__.py
karma/eval_datasets/rubrics/eka_medical_history_summary.py
karma/eval_datasets/rubrics/healthbench_dataset.py
karma/eval_datasets/rubrics/rubric_base_dataset.py
karma/io/__init__.py
karma/io/duckdb_io.py
karma/metrics/__init__.py
karma/metrics/base_metric_abs.py
karma/metrics/common_metrics.py
karma/metrics/asr/__init__.py
karma/metrics/asr/asr_metrics.py
karma/metrics/asr/asr_semantic_metrics.py
karma/metrics/asr/base_aligner.py
karma/metrics/asr/lang/__init__.py
karma/metrics/asr/lang/english_aligner.py
karma/metrics/asr/lang/hindi_aligner.py
karma_medeval-0.2.0.dist-info/licenses/LICENSE
karma_medeval-0.2.0.dist-info/METADATA
karma_medeval-0.2.0.dist-info/WHEEL
karma_medeval-0.2.0.dist-info/entry_points.txt
karma_medeval-0.2.0.dist-info/top_level.txt
karma_medeval-0.2.0.dist-info/RECORD
