Metadata-Version: 2.4
Name: karma-medeval
Version: 0.2.0
Summary: Add your description here
Home-page: https://github.com/eka-care/lucid
Author: Vasanth
Author-email: vasanth.murukuri@eka.care
Project-URL: Repository, https://github.com/eka-care/KARMA-OpenMedEvalKit
Project-URL: Documentation, https://karma.eka.care
Requires-Python: >=3.10
License-File: LICENSE
Requires-Dist: accelerate>=1.7.0
Requires-Dist: boto3>=1.35.0
Requires-Dist: click>=8.0.0
Requires-Dist: datasets>=3.6.0
Requires-Dist: duckdb>=0.9.0
Requires-Dist: evaluate>=0.4.0
Requires-Dist: mysql-connector-python>=9.3.0
Requires-Dist: pillow>=11.1.0
Requires-Dist: python-dotenv>=1.1.0
Requires-Dist: rich>=13.0.0
Requires-Dist: scikit-learn>=1.3.0
Requires-Dist: torch>=2.7.1
Requires-Dist: tqdm>=4.64.0
Requires-Dist: transformers==4.53.0
Requires-Dist: weave>=0.50.0
Requires-Dist: numpy>=2.2.6
Requires-Dist: onnxruntime>=1.22.0
Requires-Dist: google-genai>=1.24.0
Requires-Dist: openai>=1.93.0
Requires-Dist: requests>=2.32.4
Requires-Dist: simple-term-menu>=1.6.6
Requires-Dist: ipython>=8.37.0
Requires-Dist: pytrec-eval-terrier>=0.5.7
Requires-Dist: sentence-transformers>=5.0.0
Requires-Dist: faiss-cpu>=1.11.0.post1
Requires-Dist: hf_transfer==0.1.9
Provides-Extra: dev
Requires-Dist: pytest>=8.4.1; extra == "dev"
Requires-Dist: ruff>=0.12.0; extra == "dev"
Requires-Dist: ipywidgets>=8.1.7; extra == "dev"
Requires-Dist: line-profiler>=4.2.0; extra == "dev"
Provides-Extra: audio
Requires-Dist: elevenlabs>=2.5.0; extra == "audio"
Requires-Dist: indic-nlp-library>=0.92; extra == "audio"
Requires-Dist: langdetect>=1.0.9; extra == "audio"
Requires-Dist: indic-transliteration>=2.0.0; extra == "audio"
Requires-Dist: editdistance>=0.8.1; extra == "audio"
Requires-Dist: google-transliteration-api>=1.0.3; extra == "audio"
Requires-Dist: jiwer>=4.0.0; extra == "audio"
Requires-Dist: torchaudio>=2.7.1; extra == "audio"
Requires-Dist: librosa>=0.11.0; extra == "audio"
Requires-Dist: num2words>=0.5.14; extra == "audio"
Provides-Extra: all
Requires-Dist: karma-medeval[audio,dev]; extra == "all"
Dynamic: author
Dynamic: author-email
Dynamic: home-page
Dynamic: license-file
